TPool/__init__.py
TPool/wildpool.py
tpool-1.7.dist-info/licenses/LICENSE
tpool-1.7.dist-info/METADATA
tpool-1.7.dist-info/WHEEL
tpool-1.7.dist-info/top_level.txt
tpool-1.7.dist-info/RECORD
