Metadata-Version: 2.4
Name: TPool
Version: 1.7
Summary: Pool for Threads
Author-email: Ahmad Alobaid <ahmad88me@gmail.com>
License:                                  Apache License
Project-URL: Homepage, https://github.com/oeg-upm/TPool
Project-URL: Issues, https://github.com/oeg-upm/TPool/issues
Project-URL: Documentation, https://oeg-upm.github.io/TPool/
Classifier: Programming Language :: Python :: 3
Classifier: Operating System :: OS Independent
Classifier: License :: OSI Approved :: Apache Software License
Requires-Python: >=3.8
License-File: LICENSE
Dynamic: license-file
